bpetokenizer/__init__.py
bpetokenizer/base.py
bpetokenizer/tokenizer.py
bpetokenizer/version.py
bpetokenizer/pretrained/wi17k_base/wi17k_base.json
bpetokenizer-1.2.1.dist-info/METADATA
bpetokenizer-1.2.1.dist-info/WHEEL
bpetokenizer-1.2.1.dist-info/top_level.txt
bpetokenizer-1.2.1.dist-info/RECORD
