Metadata-Version: 2.1
Name: bpetokenizer
Version: 1.2.1
Summary: A Byte Pair Encoding (BPE) tokenizer, which algorithmically follows along the GPT tokenizer(tiktoken), allows you to train your own tokenizer. The tokenizer is capable of handling special tokens and uses a customizable regex pattern for tokenization(includes the gpt4 regex pattern). supports `save` and `load` tokenizers in the `json` and `file` format. The `bpetokenizer` also supports [pretrained](bpetokenizer/pretrained/) tokenizers.
Home-page: https://github.com/Hk669/bpetokenizer
Author: Hrushikesh Dokala
Author-email: hrushi669@gmail.com
License: MIT
Classifier: License :: OSI Approved :: MIT License
Classifier: Programming Language :: Python :: 3
Classifier: Operating System :: OS Independent
Requires-Python: >=3.9,<3.13
Requires-Dist: regex
Provides-Extra: dev
Requires-Dist: pytest ; extra == 'dev'
Requires-Dist: twine ; extra == 'dev'
